useful/__init__.py
useful/connections.py
useful/useful.py
useful_machines-0.1.0.post3.dist-info/LICENSE
useful_machines-0.1.0.post3.dist-info/METADATA
useful_machines-0.1.0.post3.dist-info/WHEEL
useful_machines-0.1.0.post3.dist-info/RECORD
