Metadata-Version: 2.1
Name: useful-machines
Version: 0.1.0.post3
Summary: The python sdk for useful.
Home-page: https://github.com/level-vc/useful-lite-client
License: MIT
Author: Leo Scholler
Author-email: leonardo.scholler@poatek.com
Requires-Python: >=3.9.0,<3.13
Classifier: License :: OSI Approved :: MIT License
Classifier: Programming Language :: Python :: 3
Classifier: Programming Language :: Python :: 3.9
Classifier: Programming Language :: Python :: 3.10
Classifier: Programming Language :: Python :: 3.11
Classifier: Programming Language :: Python :: 3.12
Requires-Dist: pydantic (>=2.5.2,<3.0.0)
Requires-Dist: python-dotenv (>=1.0.1,<2.0.0)
Requires-Dist: requests (>=2.31.0,<3.0.0)
Project-URL: Repository, https://github.com/level-vc/useful-lite-client.git
